marcotools/__init__.py
marcotools/filestools.py
marcotools/generaltools.py
marcotools/retools.py
marcotools/telegrambot.py
marcotools/schedule/__init__.py
marcotools-0.2.0.dist-info/LICENSE
marcotools-0.2.0.dist-info/METADATA
marcotools-0.2.0.dist-info/WHEEL
marcotools-0.2.0.dist-info/top_level.txt
marcotools-0.2.0.dist-info/RECORD
