Metadata-Version: 2.1
Name: marcotools
Version: 0.2.0
Summary: My Python tools
Home-page: https://github.com/marc0u/marcopytools
Author: Marco Urriola
Author-email: marco.urriola@gmail.com
License: UNKNOWN
Platform: UNKNOWN
Classifier: Programming Language :: Python :: 3
Classifier: License :: OSI Approved :: MIT License
Classifier: Operating System :: OS Independent
Requires-Python: >=3.6
